aiortcdc/__init__.py
aiortcdc/clock.py
aiortcdc/events.py
aiortcdc/exceptions.py
aiortcdc/jitterbuffer.py
aiortcdc/mediastreams.py
aiortcdc/rate.py
aiortcdc/rtcconfiguration.py
aiortcdc/rtcdatachannel.py
aiortcdc/rtcdtlstransport.py
aiortcdc/rtcicetransport.py
aiortcdc/rtcpeerconnection.py
aiortcdc/rtcrtpparameters.py
aiortcdc/rtcrtpreceiver.py
aiortcdc/rtcrtpsender.py
aiortcdc/rtcrtptransceiver.py
aiortcdc/rtcsctptransport.py
aiortcdc/rtcsessiondescription.py
aiortcdc/rtp.py
aiortcdc/sdp.py
aiortcdc/stats.py
aiortcdc/utils.py
aiortcdc/contrib/__init__.py
aiortcdc/contrib/media.py
aiortcdc/contrib/signaling.py
aiortc_dc-0.5.5.dist-info/LICENSE
aiortc_dc-0.5.5.dist-info/METADATA
aiortc_dc-0.5.5.dist-info/WHEEL
aiortc_dc-0.5.5.dist-info/top_level.txt
aiortc_dc-0.5.5.dist-info/RECORD
