Metadata-Version: 2.1
Name: aiortc-dc
Version: 0.5.5
Summary: data channel feature only version of aiortc which implements WebRTC and ORTC
Home-page: https://github.com/ryogrid/aiortc-dc
Author: Jeremy Lainé and Ryo Kanbayashi
Author-email: ryo.contact@gmail.com
License: BSD
Platform: UNKNOWN
Classifier: Development Status :: 3 - Alpha
Classifier: Environment :: Web Environment
Classifier: Intended Audience :: Developers
Classifier: License :: OSI Approved :: BSD License
Classifier: Operating System :: OS Independent
Classifier: Programming Language :: Python
Classifier: Programming Language :: Python :: 3
Classifier: Programming Language :: Python :: 3.5
Classifier: Programming Language :: Python :: 3.6
Classifier: Programming Language :: Python :: 3.7
Requires-Dist: aioice (<0.7.0,>=0.6.13)
Requires-Dist: attrs
Requires-Dist: crc32c
Requires-Dist: cryptography (>=2.2)
Requires-Dist: pyee
Requires-Dist: pylibsrtp (>=0.5.6)
Requires-Dist: pyopenssl
Requires-Dist: websockets (>=7.0)
